aidlab/__init__.py
aidlab/activity_type.py
aidlab/aidlab_manager.py
aidlab/aidlabsdk-linux-gnu.so
aidlab/aidlabsdk-linux-gnueabihf.so
aidlab/aidlabsdk.dll
aidlab/aidlabsdk.dylib
aidlab/body_position.py
aidlab/data_type.py
aidlab/device.py
aidlab/device_delegate.py
aidlab/wear_state.py
aidlabsdk-2.1.3.dist-info/licenses/LICENSE.md
aidlabsdk-2.1.3.dist-info/METADATA
aidlabsdk-2.1.3.dist-info/WHEEL
aidlabsdk-2.1.3.dist-info/top_level.txt
aidlabsdk-2.1.3.dist-info/RECORD
