Metadata-Version: 2.4
Name: aidlabsdk
Version: 2.1.3
Summary: Comprehensive SDK for integrating Aidlab's and Aidmed One's biofeedback and biosignal processing functionalities into your applications.
Home-page: https://www.aidlab.com
Author: Aidlab
Author-email: contact@aidlab.com
License: MIT License
Keywords: biofeedback,aidlab,aidmed,wearable technology,fitness,data analysis,healthcare,biomedical,chest strap,sdk,signals,biosignals,heart rate,ecg
Classifier: Development Status :: 5 - Production/Stable
Classifier: Intended Audience :: Developers
Classifier: Topic :: Software Development :: Libraries :: Python Modules
Classifier: License :: OSI Approved :: MIT License
Classifier: Programming Language :: Python :: 3
Requires-Python: >=3.9
License-File: LICENSE.md
Requires-Dist: bleak==0.21.1
Requires-Dist: packaging
Dynamic: author
Dynamic: author-email
Dynamic: classifier
Dynamic: description
Dynamic: description-content-type
Dynamic: home-page
Dynamic: keywords
Dynamic: license
Dynamic: license-file
Dynamic: requires-dist
Dynamic: requires-python
Dynamic: summary
